redshot/__init__.py
redshot/client.py
redshot/event.py
redshot/utils.py
redshot/auth/__init__.py
redshot/auth/auth.py
redshot/auth/local_profile_auth.py
redshot/auth/local_session_auth.py
redshot/auth/no_auth.py
redshot/auth/remote_session_auth.py
redshot/constants/__init__.py
redshot/constants/locator.py
redshot/constants/state.py
redshot/object/__init__.py
redshot/object/message.py
redshot/object/search.py
redshot-0.1.1.dist-info/LICENSE
redshot-0.1.1.dist-info/METADATA
redshot-0.1.1.dist-info/WHEEL
redshot-0.1.1.dist-info/top_level.txt
redshot-0.1.1.dist-info/RECORD
