Metadata-Version: 2.2
Name: redshot
Version: 0.1.1
Summary: RedShot is a Selenium wrapper to automate Whatsapp Web workflows
Author-email: Alexander Krentz <alexkrentz2@gmail.com>
License:                                  Apache License
Project-URL: Homepage, https://github.com/akrentz6/redshot
Project-URL: Documentation, https://github.com/akrentz6/redshot
Keywords: python,selenium,whatsapp,automation
License-File: LICENSE
Requires-Dist: selenium
